absolute_control/__init__.py
absolute_control/infrastructure/__init__.py
absolute_control/infrastructure/process.py
absolute_control/models/__init__.py
absolute_control/models/process.py
absolute_control-0.0.6.dist-info/LICENSE
absolute_control-0.0.6.dist-info/METADATA
absolute_control-0.0.6.dist-info/WHEEL
absolute_control-0.0.6.dist-info/top_level.txt
absolute_control-0.0.6.dist-info/RECORD
